{
  "url": "https://eurekaergonomic.zendesk.com/api/v2/tickets/133336.json",
  "id": 133336,
  "external_id": null,
  "via": {
    "channel": "email",
    "source": {
      "from": {
        "address": "cheesevf14@hotmail.com",
        "name": "Keith Limberg"
      },
      "to": {
        "name": "Support",
        "address": "customerservice@eurekaergonomic.com"
      },
      "rel": null
    }
  },
  "created_at": "2025-01-06T13:26:28Z",
  "updated_at": "2025-01-26T20:01:54Z",
  "generated_timestamp": 1737921714,
  "type": "incident",
  "subject": "Duplicate order",
  "raw_subject": "Duplicate order",
  "description": "I sent a question this weekend about an order that I’m never received a confirmation for. It seems I have two orders for the same item.  How can I return one?  Is it too late to stop shipment of one.  Both are under this email, cheesevf14@hotmail.com\r\n\r\nKeith Limberg",
  "priority": "normal",
  "status": "closed",
  "recipient": "customerservice@eurekaergonomic.com",
  "requester_id": 33207687072141,
  "submitter_id": 33207687072141,
  "assignee_id": 418155362151,
  "organization_id": null,
  "group_id": 360012476692,
  "collaborator_ids": [],
  "follower_ids": [],
  "email_cc_ids": [],
  "forum_topic_id": null,
  "problem_id": null,
  "has_incidents": false,
  "is_public": true,
  "due_at": null,
  "tags": [
    "erk-e33533-wb-us",
    "no",
    "no_t",
    "order_cancellation__order_cancellation_within_24_hours",
    "shopify",
    "solution_answered_question"
  ],
  "custom_fields": [
    {
      "id": 360035386891,
      "value": "EE-49176"
    },
    {
      "id": 360036048231,
      "value": "shopify"
    },
    {
      "id": 360035265932,
      "value": "erk-e33533-wb-us"
    },
    {
      "id": 14609897500813,
      "value": [
        "order_cancellation__order_cancellation_within_24_hours"
      ]
    },
    {
      "id": 14751510608525,
      "value": [
        "solution_answered_question"
      ]
    },
    {
      "id": 360035898512,
      "value": "no"
    },
    {
      "id": 32028893924749,
      "value": "no_t"
    },
    {
      "id": 40375002700557,
      "value": null
    },
    {
      "id": 31649669698061,
      "value": null
    },
    {
      "id": 33088375509133,
      "value": null
    },
    {
      "id": 34837194805901,
      "value": null
    },
    {
      "id": 33423131024141,
      "value": null
    },
    {
      "id": 33423132470925,
      "value": null
    },
    {
      "id": 33459246563725,
      "value": null
    },
    {
      "id": 33459239944717,
      "value": null
    },
    {
      "id": 33641866441357,
      "value": null
    },
    {
      "id": 33423057164941,
      "value": null
    },
    {
      "id": 33709321705101,
      "value": null
    },
    {
      "id": 34191870561037,
      "value": null
    },
    {
      "id": 33641642761613,
      "value": null
    },
    {
      "id": 360038574791,
      "value": null
    },
    {
      "id": 16433042543757,
      "value": null
    },
    {
      "id": 16433057448461,
      "value": null
    },
    {
      "id": 18562027051533,
      "value": null
    },
    {
      "id": 24007099873037,
      "value": null
    },
    {
      "id": 34301776832653,
      "value": null
    },
    {
      "id": 34358728742413,
      "value": null
    },
    {
      "id": 40901516755341,
      "value": null
    }
  ],
  "satisfaction_rating": {
    "score": "unoffered"
  },
  "sharing_agreement_ids": [],
  "custom_status_id": 3740371,
  "encoded_id": "92EYM6-E2XWE",
  "fields": [
    {
      "id": 360035386891,
      "value": "EE-49176"
    },
    {
      "id": 360036048231,
      "value": "shopify"
    },
    {
      "id": 360035265932,
      "value": "erk-e33533-wb-us"
    },
    {
      "id": 14609897500813,
      "value": [
        "order_cancellation__order_cancellation_within_24_hours"
      ]
    },
    {
      "id": 14751510608525,
      "value": [
        "solution_answered_question"
      ]
    },
    {
      "id": 360035898512,
      "value": "no"
    },
    {
      "id": 32028893924749,
      "value": "no_t"
    },
    {
      "id": 40375002700557,
      "value": null
    },
    {
      "id": 31649669698061,
      "value": null
    },
    {
      "id": 33088375509133,
      "value": null
    },
    {
      "id": 34837194805901,
      "value": null
    },
    {
      "id": 33423131024141,
      "value": null
    },
    {
      "id": 33423132470925,
      "value": null
    },
    {
      "id": 33459246563725,
      "value": null
    },
    {
      "id": 33459239944717,
      "value": null
    },
    {
      "id": 33641866441357,
      "value": null
    },
    {
      "id": 33423057164941,
      "value": null
    },
    {
      "id": 33709321705101,
      "value": null
    },
    {
      "id": 34191870561037,
      "value": null
    },
    {
      "id": 33641642761613,
      "value": null
    },
    {
      "id": 360038574791,
      "value": null
    },
    {
      "id": 16433042543757,
      "value": null
    },
    {
      "id": 16433057448461,
      "value": null
    },
    {
      "id": 18562027051533,
      "value": null
    },
    {
      "id": 24007099873037,
      "value": null
    },
    {
      "id": 34301776832653,
      "value": null
    },
    {
      "id": 34358728742413,
      "value": null
    },
    {
      "id": 40901516755341,
      "value": null
    }
  ],
  "followup_ids": [],
  "brand_id": 360004424631,
  "allow_channelback": false,
  "allow_attachments": true,
  "from_messaging_channel": false,
  "support_type": "agent"
}